{
	"configurations" : 
	[
		{
			"directories" : 
			[
				{
					"build" : ".",
					"jsonFile" : "directory-.-Debug-f5ebdc15457944623624.json",
					"minimumCMakeVersion" : 
					{
						"string" : "2.6"
					},
					"projectIndex" : 0,
					"source" : ".",
					"targetIndexes" : 
					[
						0
					]
				}
			],
			"name" : "Debug",
			"projects" : 
			[
				{
					"directoryIndexes" : 
					[
						0
					],
					"name" : "Cups",
					"targetIndexes" : 
					[
						0
					]
				}
			],
			"targets" : 
			[
				{
					"directoryIndex" : 0,
					"id" : "Cups::@6890427a1f51a3e7e1df",
					"jsonFile" : "target-Cups-Debug-6702c116413aeb6c3e9f.json",
					"name" : "Cups",
					"projectIndex" : 0
				}
			]
		}
	],
	"kind" : "codemodel",
	"paths" : 
	{
		"build" : "/home/magud23/workspace/cups/build-src-Desktop_Qt_6_6_2_GCC_64bit-Debug",
		"source" : "/home/magud23/workspace/cups/src"
	},
	"version" : 
	{
		"major" : 2,
		"minor" : 6
	}
}
